{
  "cli": {
    "version": ">= 7.8.5"
  },
  "build": {
    "development-simulator": {
      "owner": "djrepo",
      "developmentClient": true,
      "distribution": "internal",
      "ios": {
        "simulator": true
      },
      "channel": "staging"
    },
    "preview": {
      "owner": "djrepo",
      "distribution": "internal",
      "channel": "preview"
    },
    "production": {
      "owner": "djrepo",
      "channel": "production"
    }
  },
  "submit": {
    "production": {}
  }
}
